asivaflow/__init__.py
asivaflow/align.py
asivaflow/app.py
asivaflow/clean.py
asivaflow/src.py
asivaflow-0.2.dist-info/LICENSE
asivaflow-0.2.dist-info/METADATA
asivaflow-0.2.dist-info/WHEEL
asivaflow-0.2.dist-info/top_level.txt
asivaflow-0.2.dist-info/RECORD
