Metadata-Version: 2.1
Name: asivaflow
Version: 0.2
Summary: Data Reduction Pipeline
Home-page: UNKNOWN
Author: P. Saleh & T. Singh
License: MIT
Platform: UNKNOWN
License-File: LICENSE
Requires-Dist: astroalign
Requires-Dist: astropy
Requires-Dist: matplotlib
Requires-Dist: numpy
Requires-Dist: pandas
Requires-Dist: pyraf
Requires-Dist: stsci.tools (==3.4.12)
